fastapi_fastkit-1.1.5.dist-info/METADATA
fastapi_fastkit-1.1.5.dist-info/WHEEL
fastapi_fastkit-1.1.5.dist-info/entry_points.txt
fastapi_fastkit-1.1.5.dist-info/licenses/LICENSE
fastapi_fastkit/__init__.py
fastapi_fastkit/__main__.py
fastapi_fastkit/backend/__init__.py
fastapi_fastkit/backend/inspector.py
fastapi_fastkit/backend/main.py
fastapi_fastkit/backend/package_managers/__init__.py
fastapi_fastkit/backend/package_managers/base.py
fastapi_fastkit/backend/package_managers/factory.py
fastapi_fastkit/backend/package_managers/pdm_manager.py
fastapi_fastkit/backend/package_managers/pip_manager.py
fastapi_fastkit/backend/package_managers/poetry_manager.py
fastapi_fastkit/backend/package_managers/uv_manager.py
fastapi_fastkit/backend/transducer.py
fastapi_fastkit/cli.py
fastapi_fastkit/core/__init__.py
fastapi_fastkit/core/exceptions.py
fastapi_fastkit/core/settings.py
fastapi_fastkit/fastapi_project_template/PROJECT_README_TEMPLATE.md
fastapi_fastkit/fastapi_project_template/README.md
fastapi_fastkit/fastapi_project_template/__init__.py
fastapi_fastkit/fastapi_project_template/fastapi-async-crud/.env-tpl
fastapi_fastkit/fastapi_project_template/fastapi-async-crud/.gitignore-tpl
fastapi_fastkit/fastapi_project_template/fastapi-async-crud/README.md-tpl
fastapi_fastkit/fastapi_project_template/fastapi-async-crud/pyproject.toml-tpl
fastapi_fastkit/fastapi_project_template/fastapi-async-crud/requirements.txt-tpl
fastapi_fastkit/fastapi_project_template/fastapi-async-crud/scripts/format.sh-tpl
fastapi_fastkit/fastapi_project_template/fastapi-async-crud/scripts/lint.sh-tpl
fastapi_fastkit/fastapi_project_template/fastapi-async-crud/scripts/run-server.sh-tpl
fastapi_fastkit/fastapi_project_template/fastapi-async-crud/scripts/test.sh-tpl
fastapi_fastkit/fastapi_project_template/fastapi-async-crud/setup.cfg-tpl
fastapi_fastkit/fastapi_project_template/fastapi-async-crud/setup.py-tpl
fastapi_fastkit/fastapi_project_template/fastapi-async-crud/src/__init__.py-tpl
fastapi_fastkit/fastapi_project_template/fastapi-async-crud/src/api/__init__.py-tpl
fastapi_fastkit/fastapi_project_template/fastapi-async-crud/src/api/api.py-tpl
fastapi_fastkit-1.1.5.dist-info/RECORD
