Metadata-Version: 2.1
Name: FastAPI-fastkit
Version: 1.1.5
Summary: Fast, easy-to-use starter kit for new users of Python and FastAPI
Author-Email: bnbong <bbbong9@gmail.com>
License: MIT
Project-URL: Homepage, https://github.com/bnbong/FastAPI-kit
Project-URL: Repository, https://github.com/bnbong/FastAPI-kit
Project-URL: Documentation, https://bnbong.github.io/FastAPI-fastkit/
Project-URL: Changelog, https://bnbong.github.io/FastAPI-fastkit/changelog/
Requires-Python: >=3.12
Requires-Dist: click>=8.1.7
Requires-Dist: rich>=13.9.2
Provides-Extra: dev
Requires-Dist: pytest>=8.3.3; extra == "dev"
Requires-Dist: pytest-cov>=6.2.1; extra == "dev"
Requires-Dist: black>=24.10.0; extra == "dev"
Requires-Dist: pre-commit>=4.0.1; extra == "dev"
Requires-Dist: mypy>=1.12.0; extra == "dev"
Requires-Dist: isort>=5.13.2; extra == "dev"
